kratix_sdk/__init__.py
kratix_sdk/kratix_sdk.py
kratix_sdk/promise.py
kratix_sdk/resource.py
kratix_sdk/status.py
kratix_sdk/types.py
kratix_sdk/utils.py
kratix_sdk-0.4.2.dist-info/METADATA
kratix_sdk-0.4.2.dist-info/WHEEL
kratix_sdk-0.4.2.dist-info/licenses/LICENSE
kratix_sdk-0.4.2.dist-info/RECORD
