Metadata-Version: 2.4
Name: kratix-sdk
Version: 0.4.2
Summary: Kratix SDK for writing Promises workflows
Project-URL: Homepage, https://github.com/syntasso/kratix-python
Project-URL: Repository, https://github.com/syntasso/kratix-python
Project-URL: Source, https://github.com/syntasso/kratix-python
Project-URL: Documentation, https://syntasso.github.io/kratix-python
Project-URL: Bug Tracker, https://github.com/syntasso/kratix-python/issues
Project-URL: Changelog, https://github.com/syntasso/kratix-python/blob/main/CHANGELOG.md
Author-email: Syntasso <hello@syntasso.io>
License-Expression: Apache-2.0
License-File: LICENSE
Keywords: kratix,platform-engineering,promises,sdk
Classifier: Development Status :: 4 - Beta
Classifier: Intended Audience :: Developers
Classifier: License :: OSI Approved :: Apache Software License
Classifier: Programming Language :: Python
Classifier: Programming Language :: Python :: 3
Classifier: Programming Language :: Python :: 3.10
Classifier: Programming Language :: Python :: 3.11
Classifier: Programming Language :: Python :: 3.12
Classifier: Topic :: Software Development :: Build Tools
Classifier: Topic :: Utilities
Requires-Python: >=3.10
Requires-Dist: kubernetes<35,>=33.0.0
Requires-Dist: pyyaml<7,>=6.0.0
Provides-Extra: dev
Requires-Dist: pdoc>=15.0.0; extra == 'dev'
Requires-Dist: pytest>=9.0.2; extra == 'dev'
Requires-Dist: ruff>=0.14.8; extra == 'dev'
